LaueTools/CrystalParameters.py
LaueTools/FitOrient.py
LaueTools/IOLaueTools.py
LaueTools/IOimagefile.py
LaueTools/LaueAutoAnalysis.py
LaueTools/LaueDataResultsPlots.py
LaueTools/LaueGeometry.py
LaueTools/LaueToolsGUI.py
LaueTools/Lauehdf5.py
LaueTools/MessageCommand.py
LaueTools/Mg_nlut3.angles
LaueTools/Mg_nlut4.angles
LaueTools/SpotModel.py
LaueTools/Ti_nlut4.angles
LaueTools/__init__.py
LaueTools/addscriptsfolder.py
LaueTools/annot.py
LaueTools/blissdatafolderstructure.py
LaueTools/buildsummary.py
LaueTools/calib_.cor
LaueTools/cli.py
LaueTools/cli_add_material.py
LaueTools/cliques.py
LaueTools/copyexamplescripts.py
LaueTools/daxmgui.py
LaueTools/dict_LaueTools.py
LaueTools/dragpoints.py
LaueTools/elasticity.py
LaueTools/findorient.py
LaueTools/fit2Dintensity.py
LaueTools/fit2Dintensity_Lorentz.py
LaueTools/fitfilereader.py
LaueTools/generaltools.py
LaueTools/graingraph.py
LaueTools/imageprocessing.py
LaueTools/imagescollector.py
LaueTools/indexingAnglesLUT.py
LaueTools/indexingImageMatching.py
LaueTools/indexingSpotsSet.py
LaueTools/indexrefine.py
LaueTools/lauecore.py
LaueTools/lauetools.py
LaueTools/lauetools_config.json
LaueTools/logfile_reader.py
LaueTools/mapanalyzer.py
LaueTools/matchingrate.py
LaueTools/materials.yaml
LaueTools/multigrainsSimulator.py
LaueTools/orientations.py
LaueTools/parabolmirror.py
LaueTools/param_multigrain.py
LaueTools/peaklistfit2d.py
LaueTools/peaksearch.py
LaueTools/plotmap.py
LaueTools/plotmeshspecGUI.py
LaueTools/readmccd.py
LaueTools/rectangle.py
LaueTools/show2DmapGUI.py
LaueTools/spottracking.py
LaueTools/tifffile.py
LaueTools/warning.py
LaueTools/wyckpos_lauetools.py
LaueTools/Daxm/DaxmAnalyzerGui.py
LaueTools/Daxm/__init__.py
LaueTools/Daxm/classes/__init__.py
LaueTools/Daxm/classes/example.wscan
LaueTools/Daxm/classes/source.py
LaueTools/Daxm/classes/wire.py
LaueTools/Daxm/classes/calibration/__init__.py
LaueTools/Daxm/classes/calibration/calib.py
LaueTools/Daxm/classes/calibration/diffraction.py
lauetools-3.1.45.dist-info/METADATA
lauetools-3.1.45.dist-info/WHEEL
lauetools-3.1.45.dist-info/entry_points.txt
lauetools-3.1.45.dist-info/top_level.txt
lauetools-3.1.45.dist-info/RECORD
