Metadata-Version: 2.4
Name: lauetools
Version: 3.1.45
Summary: Distribution of LaueTools Package from github.com/BM32ESRF/Lauetools repository for pip
Home-page: https://github.com/BM32ESRF/lauetools
Author: J S Micha
Author-email: micha@esrf.fr
License: MIT
Keywords: Lauetools x-ray scattering data analysis GUI Laue
Classifier: Programming Language :: Python :: 3.12
Classifier: Programming Language :: Python :: 3.11
Classifier: Programming Language :: Python :: 3.10
Classifier: Programming Language :: Python :: 3.9
Classifier: Programming Language :: Python :: 3.8
Classifier: Programming Language :: Python :: 3.7
Classifier: Programming Language :: Python :: 3.6
Classifier: Programming Language :: Python :: 3.5
Classifier: Programming Language :: Python :: 2.7
Classifier: License :: OSI Approved :: MIT License
Classifier: Operating System :: OS Independent
Requires-Python: >=2.6 , <3.13
Requires-Dist: docutils>=0.3
Requires-Dist: numpy>=1.0.3
Requires-Dist: scipy>=0.15.0
Requires-Dist: matplotlib>=2.0.0
Requires-Dist: wxpython>=3.0
Requires-Dist: networkx>=2.1
Requires-Dist: tqdm>=4.60.0
Requires-Dist: h5py>=3.1
Requires-Dist: scikit-image>=0.1.0
Requires-Dist: astropy>=3.0
Requires-Dist: fabio>=0.11.0
Requires-Dist: PyYAML>=6.0.1
Dynamic: author
Dynamic: author-email
Dynamic: classifier
Dynamic: description
Dynamic: description-content-type
Dynamic: home-page
Dynamic: keywords
Dynamic: license
Dynamic: requires-dist
Dynamic: requires-python
Dynamic: summary
